{
    "original_title": "Annual freshwater withdrawals, total (billion cubic meters) ",
    "original_indicator_code": "ER.H2O.FWTL.K3",
    "title": "Frischwasserverbrauch",
    "indicator_code": "",
    "short_indicator_description_de": "Jährlicher Frischwasserverbrauch in Milliarden Kubikmeter",
    "short_indicator_description_en": "Annual freshwater withdrawal in cubic meters per capita",
    "long_indicator_description_de": "Jährlicher Frischwasserverbrauch ist der vollumfängliche Wasserverbrauch in Milliarden Kubikmeter für landwirtschaftlichen, industriellen sowie privaten Verbrauch. Verdunstungen in Sammelbecken bleiben ungezählt. Der Verbrauch beinhaltet auch Wasser von Entsalzungsanlagen in Ländern wo diese eine wesentliche Wasserquelle sind. Der Verbrauch kann 100 Prozent der erneuerbaren Quellen übersteigen wo  der Verbrauch auf nichterneuerbare Grundwasserschichten oder Entsalzungsanlagen zurückgeht.",
    "long_indicator_description_en": "Annual freshwater withdrawals refer to total water withdrawals in cubic meter per capita, not counting evaporation losses from storage basins. Withdrawals also include water from desalination plants in countries where they are a significant source. Withdrawals can exceed 100 percent of total renewable resources where extraction from nonrenewable aquifers or desalination plants is considerable or where there is significant water reuse. Withdrawals for agriculture and industry are total withdrawals for irrigation and livestock production and for direct industrial use (including withdrawals for cooling thermoelectric plants). Withdrawals for domestic uses include drinking water, municipal use or supply, and use for public services, commercial establishments, and homes.",
    "unit": {
        "base": "cm3/Jahr",
        "multiplier": "1000000000"
    },
    "target": {
        "type": "less",
        "value": "200",
        "breakpoints": "A) Wertung 1-5,1,2,3,4,5 B) Methode,200,400,600,800,1000"
    },
    "explanation_of_target": "",
    "target_reference": "",
    "source_of_data": "World Bank",
    "source_note": "Annual freshwater withdrawals refer to total water withdrawals, not counting evaporation losses from storage basins. Withdrawals also include water from desalination plants in countries where they are a significant source. Withdrawals can exceed 100 percent of total renewable resources where extraction from nonrenewable aquifers or desalination plants is considerable or where there is significant water reuse. Withdrawals for agriculture and industry are total withdrawals for irrigation and livestock production and for direct industrial use (including withdrawals for cooling thermoelectric plants). Withdrawals for domestic uses include drinking water, municipal use or supply, and use for public services, commercial establishments, and homes. Data are for the most recent year available for 1987-2002.",
    "indicator_type": "global",
    "indicator_source": {
        "value": "OKF",
        "type": "inofficial"
    },
    "link": "http://data.worldbank.org/indicator/ER.H2O.FWTL.K3",
    "tags": [
        "ecologic"
    ],
    "sdg": [
        6
    ],
    "most_recent_year": 2013,
    "ministerial_responsibility": [
        "BMUB"
    ],
    "licence": "",
    "quality_of_indicator": "",
    "maintainer": "tbd",
    "additional_information": "",
    "scoring": [
        {
            "timestamp_data_host": "02-10-2015",
            "timestamp": "02-10-2015",
            "countries": [
                {
                    "name": "Australia",
                    "value": 961.229992964,
                    "score": 5
                },
                {
                    "name": "Austria",
                    "value": 428.4965057088,
                    "score": 3
                },
                {
                    "name": "Belgium",
                    "value": 553.7537080608,
                    "score": 3
                },
                {
                    "name": "Bulgaria",
                    "value": 846.7691101839,
                    "score": 5
                },
                {
                    "name": "Bosnia and Herzegovina",
                    "value": 86.1808372586,
                    "score": 1
                },
                {
                    "name": "Brazil",
                    "value": 363.1151167895,
                    "score": 2
                },
                {
                    "name": "Canada",
                    "value": 1187.3804864259,
                    "score": 5
                },
                {
                    "name": "Switzerland",
                    "value": 319.1607951377,
                    "score": 2
                },
                {
                    "name": "Chile",
                    "value": 1994.6351464396,
                    "score": 5
                },
                {
                    "name": "China",
                    "value": 406.1512750409,
                    "score": 3
                },
                {
                    "name": "Cyprus",
                    "value": 159.4926746055,
                    "score": 1
                },
                {
                    "name": "Czech Republic",
                    "value": 161.6468608827,
                    "score": 1
                },
                {
                    "name": "Germany",
                    "value": 399.3101453643,
                    "score": 2
                },
                {
                    "name": "Denmark",
                    "value": 117.0303028691,
                    "score": 1
                },
                {
                    "name": "Spain",
                    "value": 699.4995884244,
                    "score": 4
                },
                {
                    "name": "Estonia",
                    "value": 1367.1882433991,
                    "score": 5
                },
                {
                    "name": "Finland",
                    "value": 299.0704290727,
                    "score": 2
                },
                {
                    "name": "France",
                    "value": 477.5935087158,
                    "score": 3
                },
                {
                    "name": "UK",
                    "value": 201.9830112291,
                    "score": 2
                },
                {
                    "name": "Greece",
                    "value": 864.3205624517,
                    "score": 5
                },
                {
                    "name": "Croatia",
                    "value": 148.3807005948,
                    "score": 1
                },
                {
                    "name": "Hungary",
                    "value": 567.8549674077,
                    "score": 3
                },
                {
                    "name": "India",
                    "value": 587.5125211097,
                    "score": 3
                },
                {
                    "name": "Ireland",
                    "value": 171.265581103,
                    "score": 1
                },
                {
                    "name": "Iceland",
                    "value": 503.6799159923,
                    "score": 3
                },
                {
                    "name": "Israel",
                    "value": 237.8488917021,
                    "score": 2
                },
                {
                    "name": "Italy",
                    "value": 740.3435745245,
                    "score": 4
                },
                {
                    "name": "Japan",
                    "value": 708.2413684066,
                    "score": 4
                },
                {
                    "name": "South Korea",
                    "value": 505.1170619203,
                    "score": 3
                },
                {
                    "name": "Lithuania",
                    "value": 811.7916665387,
                    "score": 5
                },
                {
                    "name": "Luxembourg",
                    "value": 108.2589727267,
                    "score": 1
                },
                {
                    "name": "Latvia",
                    "value": 210.0132087255,
                    "score": 2
                },
                {
                    "name": "Mexico",
                    "value": 640.4232286753,
                    "score": 4
                },
                {
                    "name": "Macedonia",
                    "value": 495.2725082806,
                    "score": 3
                },
                {
                    "name": "Malta",
                    "value": 126.1101908265,
                    "score": 1
                },
                {
                    "name": "Netherlands",
                    "value": 629.5173132984,
                    "score": 4
                },
                {
                    "name": "Norway",
                    "value": 572.1822845434,
                    "score": 3
                },
                {
                    "name": "New Zealand",
                    "value": 1053.9503736391,
                    "score": 5
                },
                {
                    "name": "Poland",
                    "value": 314.773877737,
                    "score": 2
                },
                {
                    "name": "Portugal",
                    "value": 813.9540363628,
                    "score": 5
                },
                {
                    "name": "Romania",
                    "value": 345.3368352511,
                    "score": 2
                },
                {
                    "name": "Russia",
                    "value": 460.2989736397,
                    "score": 3
                },
                {
                    "name": "Serbia",
                    "value": 575.08119866,
                    "score": 3
                },
                {
                    "name": "Slovakia",
                    "value": 126.9722687398,
                    "score": 1
                },
                {
                    "name": "Slovenia",
                    "value": 456.789728341,
                    "score": 3
                },
                {
                    "name": "Sweden",
                    "value": 269.9814387761,
                    "score": 2
                },
                {
                    "name": "Turkey",
                    "value": 528.1016728207,
                    "score": 3
                },
                {
                    "name": "USA",
                    "value": 1500.358831639,
                    "score": 5
                },
                {
                    "name": "South Africa",
                    "value": 231.4731098707,
                    "score": 2
                }
            ]
        }
    ]
}
