{
    "original_title": "Wastewater Treatment (WASTECXN) - Percentage of anthropogenic wastewater that receives treatment (%)",
    "original_indicator_code": "WASTECXN",
    "title": "Abwasseraufbereitung",
    "short_indicator_description": {
        "de": "Beschreibt den Anteil des anthropogenen Abwassers das aufbereitet wird.",
        "en": "Share of wastewater that receives treatment."
    },
    "long_indicator_description": {
        "de": "Ungereinigtes Abwasser kann die Ökosysteme schädigen. Abwasser ist hier definiert als Wasser von Badewannen, Waschbecken, Waschmaschinen und Haushaltsgeräten (graues Wasser), Wasser aus Toiletten (schwarzes Wasser) und Wasser aus der Industrie, das chemische Verunreinigungen beinhalten kann. Die Reinigung von Abwasser ist kritisch für ein nachhaltiges Umweltmanagement. Die hier genutzte Indikator wurde von dem Yale Center for Environmental Law & Policy (YCELP) entwickelt. Er beruht auf Daten von Umweltstatistiken nationaler Behörden, OECD Daten, der UN Statistikbehörde (UNSD), der UN Organisation für Ernährung und Landwirtschaft (FAO), Beiträgen des Pinsent Masons Water Yearbook sowie auf Expertenrat der im Rahmen des Yale Environmental Performance Index eingeholt wurde. Mehr englischsprachige Informationen sind hier erhältlich: http://epi.yale.edu/our-methods/water-resources. (Source EPI).",
        "en": "Untreated sewage can disrupt the functioning of downstream ecosystems. Wastewater is comprised of domestic grey-water (water from baths, sinks, washing machines, and kitchen appliances) and black-water (water from toilets), as well industrial wastewater that may have additional chemical contaminants. The practice of water treatment is vital for the health of aquatic systems, provides health benefits for local residents, and ensures that clean water is available for re-use. Good wastewater management is especially relevant for areas facing more significant impacts of climate change and rapid population growth, since such areas may face more constrained water resources in the future. This indicator was developed by the Yale Center for Environmental Law & Policy (YCELP). It is based on data from national statistical offices, OECD data, the UN Statistical Organisation (UNSD), the UN organisation for food and agriculture (FAO), contributions of the Pinsent Masons Water Yearbook as well as expert advise. More information is available here: http://epi.yale.edu/our-methods/water-resources. (Source EPI)."
    },
    "baseunit": "%",
    "target": {
        "value": "100",
        "type": "more",
        "rating": [80,60,40,20]
    },
    "tags": [
        "ecologic"
    ],
    "sdg": [
        6
    ],
    "ministerial_responsibility": [
        "BMUB"
    ],
    "scoring": [
        {
            "type": "national",
            "maintainer": "tbd",
            "source": {
                "link": "http://epi.yale.edu/our-methods/water-resources",
                "note": "This indicator tracks how well countries treat wastewater from households and industrial sources before it is dumped into the enviroment. It tracks the performance of basic wastewater management.",
                "publisher": "Yale Environmental Performance Index, Malik, O. (2013). Global database of National Wastewater Treatment. New Haven, CT: Yale Center for Environmental Law & Policy., Enviromental performance Index, EPI 2014",
                "value": "OKF",
                "type": "inofficial"
            },
            "timestamp": "2015-10-29",
            "timestamp_data_host": "2015-10-29",
            "countries": [
                {
                    "score": 1,
                    "value": 92.3333333333,
                    "name": "Australia"
                },
                {
                    "name": "Austria",
                    "value": 79.05,
                    "score": 2
                },
                {
                    "name": "Belgium",
                    "score": 2,
                    "value": 60.0044564267
                },
                {
                    "value": 10.8687777778,
                    "score": 5,
                    "name": "Brazil"
                },
                {
                    "value": 80.4199488333,
                    "score": 1,
                    "name": "Canada"
                },
                {
                    "value": 68.8484293939,
                    "score": 2,
                    "name": "Chile"
                },
                {
                    "score": 5,
                    "value": 18.1799122376,
                    "name": "China"
                },
                {
                    "score": 5,
                    "value": 13.2329178571,
                    "name": "Croatia"
                },
                {
                    "score": 2,
                    "value": 75.68236485,
                    "name": "Czech Republic"
                },
                {
                    "name": "Denmark",
                    "score": 1,
                    "value": 93.45
                },
                {
                    "name": "Estonia",
                    "score": 2,
                    "value": 75.2707438017
                },
                {
                    "score": 1,
                    "value": 84.25,
                    "name": "Finland"
                },
                {
                    "value": 83.7991333333,
                    "score": 1,
                    "name": "France"
                },
                {
                    "value": 95.18054,
                    "score": 1,
                    "name": "Germany"
                },
                {
                    "name": "Greece",
                    "score": 1,
                    "value": 87.3333333333
                },
                {
                    "name": "Hungary",
                    "value": 58.6191666667,
                    "score": 3
                },
                {
                    "score": 3,
                    "value": 51.9428571429,
                    "name": "Iceland"
                },
                {
                    "value": 10.487603285,
                    "score": 5,
                    "name": "India"
                },
                {
                    "name": "Ireland",
                    "score": 1,
                    "value": 87.4655833333
                },
                {
                    "name": "Israel",
                    "score": 1,
                    "value": 88.4031733333
                },
                {
                    "name": "Italy",
                    "value": 91.4375955171,
                    "score": 1
                },
                {
                    "value": 71.26,
                    "score": 2,
                    "name": "Japan"
                },
                {
                    "value": 49.625,
                    "score": 3,
                    "name": "Latvia"
                },
                {
                    "value": 45.82,
                    "score": 3,
                    "name": "Lithuania"
                },
                {
                    "value": 95,
                    "score": 1,
                    "name": "Luxembourg"
                },
                {
                    "name": "Mexico",
                    "score": 4,
                    "value": 37.4474987012
                },
                {
                    "name": "Netherlands",
                    "score": 1,
                    "value": 98.8181818182
                },
                {
                    "name": "New Zealand",
                    "value": 77.9,
                    "score": 2
                },
                {
                    "name": "Norway",
                    "value": 77.0533426713,
                    "score": 2
                },
                {
                    "score": 2,
                    "value": 60.7272727273,
                    "name": "Poland"
                },
                {
                    "value": 70.3305816327,
                    "score": 2,
                    "name": "Portugal"
                },
                {
                    "name": "Russia",
                    "score": 4,
                    "value": 21.5
                },
                {
                    "score": 3,
                    "value": 57.6351333333,
                    "name": "Slovakia"
                },
                {
                    "name": "Slovenia",
                    "value": 53.9918962121,
                    "score": 3
                },
                {
                    "score": 4,
                    "value": 27.85875,
                    "name": "South Africa"
                },
                {
                    "name": "South Korea",
                    "score": 1,
                    "value": 83.68
                },
                {
                    "score": 1,
                    "value": 92.8272,
                    "name": "Spain"
                },
                {
                    "name": "Sweden",
                    "value": 87.8571428571,
                    "score": 1
                },
                {
                    "value": 96.95,
                    "score": 1,
                    "name": "Switzerland"
                },
                {
                    "value": 48.9315272727,
                    "score": 3,
                    "name": "Turkey"
                },
                {
                    "score": 1,
                    "value": 97.927095,
                    "name": "UK"
                },
                {
                    "name": "USA",
                    "score": 2,
                    "value": 63.665
                }
            ]
        }
    ]
}
